jenkins_job_builder-6.4.4.dist-info/licenses/AUTHORS
jenkins_job_builder-6.4.4.dist-info/licenses/LICENSE
jenkins_jobs/__init__.py
jenkins_jobs/__main__.py
jenkins_jobs/alphanum.py
jenkins_jobs/builder.py
jenkins_jobs/cache.py
jenkins_jobs/cached_property.py
jenkins_jobs/config.py
jenkins_jobs/constants.py
jenkins_jobs/defaults.py
jenkins_jobs/dimensions.py
jenkins_jobs/errors.py
jenkins_jobs/expander.py
jenkins_jobs/formatter.py
jenkins_jobs/job.py
jenkins_jobs/loader.py
jenkins_jobs/loc_loader.py
jenkins_jobs/macro.py
jenkins_jobs/parallel.py
jenkins_jobs/position.py
jenkins_jobs/project.py
jenkins_jobs/registry.py
jenkins_jobs/root_base.py
jenkins_jobs/roots.py
jenkins_jobs/utils.py
jenkins_jobs/version.py
jenkins_jobs/view.py
jenkins_jobs/xml_config.py
jenkins_jobs/yaml_objects.py
jenkins_jobs/cli/__init__.py
jenkins_jobs/cli/entry.py
jenkins_jobs/cli/parser.py
jenkins_jobs/cli/subcommand/__init__.py
jenkins_jobs/cli/subcommand/base.py
jenkins_jobs/cli/subcommand/delete.py
jenkins_jobs/cli/subcommand/delete_all.py
jenkins_jobs/cli/subcommand/get_plugins_info.py
jenkins_jobs/cli/subcommand/list.py
jenkins_jobs/cli/subcommand/test.py
jenkins_jobs/cli/subcommand/update.py
jenkins_jobs/modules/__init__.py
jenkins_jobs/modules/base.py
jenkins_jobs/modules/builders.py
jenkins_jobs/modules/general.py
jenkins_jobs/modules/helpers.py
jenkins_jobs/modules/hipchat_notif.py
jenkins_jobs/modules/hudson_model.py
jenkins_jobs/modules/metadata.py
jenkins_jobs/modules/notifications.py
jenkins_jobs/modules/parameters.py
jenkins_jobs/modules/project_externaljob.py
jenkins_jobs/modules/project_flow.py
jenkins_jobs/modules/project_folder.py
jenkins_jobs/modules/project_freestyle.py
jenkins_jobs/modules/project_githuborg.py
jenkins_jobs/modules/project_matrix.py
jenkins_jobs/modules/project_maven.py
jenkins_jobs/modules/project_multibranch.py
jenkins_jobs/modules/project_multijob.py
jenkins_jobs/modules/project_pipeline.py
jenkins_jobs/modules/project_workflow.py
jenkins_jobs/modules/properties.py
jenkins_jobs/modules/publishers.py
jenkins_jobs/modules/reporters.py
jenkins_job_builder-6.4.4.dist-info/METADATA
jenkins_job_builder-6.4.4.dist-info/WHEEL
jenkins_job_builder-6.4.4.dist-info/entry_points.txt
jenkins_job_builder-6.4.4.dist-info/pbr.json
jenkins_job_builder-6.4.4.dist-info/top_level.txt
jenkins_job_builder-6.4.4.dist-info/RECORD
