Metadata-Version: 2.4
Name: jenkins-job-builder
Version: 6.4.4
Summary: Manage Jenkins jobs with YAML
Home-page: https://jenkins-job-builder.readthedocs.io/en/latest/
Author: OpenStack Infrastructure Team
Author-email: jenkins-job-builder@googlegroups.com
License: Apache License, Version 2.0
Classifier: Topic :: Utilities
Classifier: Environment :: Console
Classifier: Intended Audience :: Developers
Classifier: Intended Audience :: Information Technology
Classifier: Intended Audience :: System Administrators
Classifier: License :: OSI Approved :: Apache Software License
Classifier: Operating System :: OS Independent
Classifier: Programming Language :: Python
Classifier: Programming Language :: Python :: 3
Classifier: Programming Language :: Python :: 3.8
Classifier: Programming Language :: Python :: 3.9
Classifier: Programming Language :: Python :: 3.10
Classifier: Programming Language :: Python :: 3.11
Classifier: Programming Language :: Python :: 3.12
License-File: LICENSE
License-File: AUTHORS
Requires-Dist: six>=1.9.0
Requires-Dist: PyYAML>=3.13
Requires-Dist: pbr>=1.8
Requires-Dist: python-jenkins>=1.8.2
Requires-Dist: fasteners
Requires-Dist: Jinja2
Requires-Dist: packaging
Requires-Dist: setuptools
Requires-Dist: stevedore<2,>=1.17.1; python_version < "3.0"
Requires-Dist: stevedore>=1.17.1; python_version >= "3.0"
Dynamic: author
Dynamic: author-email
Dynamic: classifier
Dynamic: description
Dynamic: home-page
Dynamic: license
Dynamic: license-file
Dynamic: provides-extra
Dynamic: requires-dist
Dynamic: summary
